django_pwdprotect-1.0.1.dist-info/DESCRIPTION.rst
django_pwdprotect-1.0.1.dist-info/METADATA
django_pwdprotect-1.0.1.dist-info/RECORD
django_pwdprotect-1.0.1.dist-info/WHEEL
django_pwdprotect-1.0.1.dist-info/metadata.json
django_pwdprotect-1.0.1.dist-info/top_level.txt
pwdprotect/__init__.py
pwdprotect/admin.py
pwdprotect/apps.py
pwdprotect/middleware.py
pwdprotect/models.py
pwdprotect/migrations/0001_initial.py
pwdprotect/migrations/__init__.py
