Metadata-Version: 2.0
Name: django-pwdprotect
Version: 1.0.1
Summary: Password-protected URLs for Django
Home-page: https://gitlab.com/unplugstudio/django-pwdprotect
Author: Ed Rivas
Author-email: ed@unplug.studio
License: MIT
Keywords: django security password page middleware
Platform: UNKNOWN
Classifier: Development Status :: 5 - Production/Stable
Classifier: Intended Audience :: Developers
Classifier: Topic :: Software Development :: Libraries
Classifier: License :: OSI Approved :: MIT License
Classifier: Programming Language :: Python :: 2
Classifier: Programming Language :: Python :: 2.7
Classifier: Programming Language :: Python :: 3
Classifier: Programming Language :: Python :: 3.4
Classifier: Programming Language :: Python :: 3.5
Classifier: Programming Language :: Python :: 3.6
